tap_delighted/__init__.py
tap_delighted/client.py
tap_delighted/streams.py
tap_delighted/tap.py
tap_delighted-0.0.1.dist-info/LICENSE
tap_delighted-0.0.1.dist-info/METADATA
tap_delighted-0.0.1.dist-info/WHEEL
tap_delighted-0.0.1.dist-info/entry_points.txt
tap_delighted-0.0.1.dist-info/RECORD
