Metadata-Version: 2.1
Name: tap-delighted
Version: 0.0.1
Summary: `tap-delighted` is a Singer tap for Delighted, built with the Meltano Singer SDK.
License: Apache-2.0
Keywords: ELT,Delighted
Author: Tobias Cadee
Author-email: tobias.cadee@ticketswap.com
Requires-Python: >=3.8,<4
Classifier: License :: OSI Approved :: Apache Software License
Classifier: Programming Language :: Python :: 3
Classifier: Programming Language :: Python :: 3.8
Classifier: Programming Language :: Python :: 3.9
Classifier: Programming Language :: Python :: 3.10
Classifier: Programming Language :: Python :: 3.11
Provides-Extra: s3
Requires-Dist: delighted (>=4.1.0,<5.0.0)
Requires-Dist: fs-s3fs (>=1.1.1,<1.2.0) ; extra == "s3"
Requires-Dist: requests (>=2.31.0,<2.32.0)
Requires-Dist: singer-sdk (>=0.33.0,<0.34.0)
